[{"prodName":"상품명: 웰킵스 스마트 미세먼지황사마스크 KF94 대형 10개입","prodStatus":false,"prodPath":"https://smartstore.naver.com/welkeeps/products/4903264925","index":0,"crawlTime":"2020-06-19T01:40:04.516Z","prodImg":"https://shop-phinf.pstatic.net/20200422_51/1587541576999x91El_JPEG/24903119624964563_825718812.jpg?type=m510"},{"prodName":"상품명: 웰킵스 스마트 미세먼지황사마스크 KF80 대형 10개입","prodStatus":false,"prodPath":"https://smartstore.naver.com/welkeeps/products/4903263687","index":1,"crawlTime":"2020-06-19T01:40:08.071Z","prodImg":"https://shop-phinf.pstatic.net/20200422_25/1587541537331doXs4_JPEG/24903079827400258_1163486055.jpg?type=m510"},{"prodName":"상품명: 웰킵스 리얼블랙 미세먼지황사마스크 KF94 중형 10개입","prodStatus":false,"prodPath":"https://smartstore.naver.com/welkeeps/products/4903261406","index":2,"crawlTime":"2020-06-19T01:40:11.589Z","prodImg":"https://shop-phinf.pstatic.net/20200422_270/1587541482214lWy9j_JPEG/24903024841384086_1852960799.jpg?type=m510"},{"prodName":"상품명: 웰킵스 리얼블랙 미세먼지황사마스크 KF94 대형 10개입","prodStatus":false,"prodPath":"https://smartstore.naver.com/welkeeps/products/4903258545","index":3,"crawlTime":"2020-06-19T01:40:15.027Z","prodImg":"https://shop-phinf.pstatic.net/20200422_61/1587541442530RTnpQ_JPEG/24902985156167112_986882160.jpg?type=m510"},{"prodName":"상품명: 웰킵스 프리미엄 미세먼지황사마스크 KF80 소형 10개입","prodStatus":false,"prodPath":"https://smartstore.naver.com/welkeeps/products/4903256871","index":4,"crawlTime":"2020-06-19T01:40:18.784Z","prodImg":"https://shop-phinf.pstatic.net/20200422_115/1587541389646iIiSa_JPEG/24902932270677653_1079145765.jpg?type=m510"},{"prodName":"상품명: 웰킵스 프리미엄 미세먼지황사마스크 KF80 대형 10개입","prodStatus":false,"prodPath":"https://smartstore.naver.com/welkeeps/products/4903252805","index":5,"crawlTime":"2020-06-19T01:40:22.232Z","prodImg":"https://shop-phinf.pstatic.net/20200422_72/1587541224522iWhCH_JPEG/24902767148378105_914648277.jpg?type=m510"},{"prodName":"상품명: 웰킵스언택트마스크 KF-AD 비말차단용 대형 3개입","prodStatus":false,"prodPath":"https://smartstore.naver.com/welkeeps/products/4962197585","index":6,"crawlTime":"2020-06-19T01:40:26.409Z","prodImg":"https://shop-phinf.pstatic.net/20200608_238/1591573915518NgnFx_JPEG/28934654150497038_2139419424.jpg?type=m510"},{"prodName":"상품명: 6월 19일 품절 [10개입] KF94 아에르 스탠다드 베이직 마스크","prodStatus":false,"prodPath":"https://smartstore.naver.com/aer-shop/products/4722827602","index":7,"crawlTime":"2020-06-19T01:40:30.089Z","prodImg":"https://shop-phinf.pstatic.net/20200618_180/1592465582992vBebQ_JPEG/29827125586269312_1423597452.jpg?type=m510"},{"prodName":"상품명: 6월 19일 품절 [10개입] KF94 컬러 마스크/한정판 스페셜 컬러/와인","prodStatus":false,"prodPath":"https://smartstore.naver.com/aer-shop/products/4969187572","index":8,"crawlTime":"2020-06-19T01:40:33.555Z","prodImg":"https://shop-phinf.pstatic.net/20200615_133/1592203041494Kg9qo_JPEG/29562876033325297_757355260.jpg?type=m510"},{"prodName":"상품명: 6월 19일 품절 [10개입] KF94 컬러 마스크/한정판 스페셜 컬러/그린","prodStatus":false,"prodPath":"https://smartstore.naver.com/aer-shop/products/4977838346","index":9,"crawlTime":"2020-06-19T01:40:37.105Z","prodImg":"https://shop-phinf.pstatic.net/20200618_3/1592466110996kgWqI_JPEG/29826849605927842_656887587.jpg?type=m510"},{"prodName":"상품명: [닥터퓨리] KF94 끈조절 미세먼지 황사마스크 20매 (개별 낱개포장)","prodStatus":false,"prodPath":"https://smartstore.naver.com/mfbshop/products/4735160554","index":10,"crawlTime":"2020-06-19T01:40:41.350Z","prodImg":"https://shop-phinf.pstatic.net/20191119_243/1574153821306RG4oJ_PNG/11517209831114473_2059076338.png?type=m510"},{"prodName":"상품명: [닥터퓨리] KF94 끈조절 블랙 미세먼지 황사마스크 20매 (개별 낱개포장)","prodStatus":false,"prodPath":"https://smartstore.naver.com/mfbshop/products/4735164530","index":11,"crawlTime":"2020-06-19T01:40:45.603Z","prodImg":"https://shop-phinf.pstatic.net/20191119_84/15741553012909fui0_PNG/11518689815460715_839415566.png?type=m510"},{"prodName":"상품명: [닥터퓨리] KF94 미세먼지 황사마스크 20매 (개별 낱개포장)","prodStatus":false,"prodPath":"https://smartstore.naver.com/mfbshop/products/4072435942","index":12,"crawlTime":"2020-06-19T01:40:49.728Z","prodImg":"https://shop-phinf.pstatic.net/20191114_90/1573697831363MXTmg_PNG/11061219890648423_1983943751.png?type=m510"},{"prodName":"상품명: [닥터퓨리] KF94 스타일리시 블랙 미세먼지 황사마스크 20매 (개별 낱개포장)","prodStatus":false,"prodPath":"https://smartstore.naver.com/mfbshop/products/4680268551","index":13,"crawlTime":"2020-06-19T01:40:53.931Z","prodImg":"https://shop-phinf.pstatic.net/20191114_97/1573697749695lQAoX_PNG/11061138223111516_659755075.png?type=m510"},{"prodName":"상품명: [닥터퓨리] KF94 미세먼지 황사마스크 30매 (뽑아쓰는 번들포장)","prodStatus":false,"prodPath":"https://smartstore.naver.com/mfbshop/products/4072573492","index":14,"crawlTime":"2020-06-19T01:40:59.451Z","prodImg":"https://shop-phinf.pstatic.net/20190925_38/1569375864730FBen6_PNG/6739253265698858_1446444881.png?type=m510"},{"prodName":"상품명: 뉴네퓨어 황사마스크 화이트 5매 - 식약처허가 KF94 미세먼지 끈길이조절","prodStatus":false,"prodPath":"https://smartstore.naver.com/gonggami/products/4705579501","index":15,"crawlTime":"2020-06-19T01:41:02.764Z","prodImg":"https://shop-phinf.pstatic.net/20200604_50/15912734419444Yf4K_JPEG/28633276483115141_2070346357.jpg?type=m510"},{"prodName":"상품명: [입고미정]  KF94 국대 황사 미세먼지 마스크 20매","prodStatus":false,"prodPath":"https://smartstore.naver.com/korea-mask/products/4825762296","index":16,"crawlTime":"2020-06-19T01:41:06.244Z","prodImg":"https://shop-phinf.pstatic.net/20200218_8/1582015020328w8g0O_JPEG/19375758961058864_1829744585.jpg?type=m510"},{"prodName":"상품명: 위케어 황사 미세먼지마스크 KF94 성인용 60매","prodStatus":false,"prodPath":"https://smartstore.naver.com/wiicare/products/3922733602","index":17,"crawlTime":"2020-06-19T01:41:10.527Z","prodImg":"https://shop-phinf.pstatic.net/20200617_230/15923688611717zlFL_JPEG/29732249658183073_1984655320.jpg?type=m510"},{"prodName":"상품명: 위케어 블랙 10매 1인 1개","prodStatus":false,"prodPath":"https://smartstore.naver.com/wiicare/products/4242262742","index":18,"crawlTime":"2020-06-19T01:41:15.408Z","prodImg":"https://shop-phinf.pstatic.net/20200617_123/1592369073183EWSL9_JPEG/29732461695509349_1481899980.jpg?type=m510"},{"prodName":"상품명: 위케어 성인용 20매 1인 1개","prodStatus":false,"prodPath":"https://smartstore.naver.com/wiicare/products/3922699232","index":19,"crawlTime":"2020-06-19T01:41:20.766Z","prodImg":"https://shop-phinf.pstatic.net/20200617_106/1592368723520J1b42_JPEG/29728558059342162_919139432.jpg?type=m510"},{"prodName":"상품명: 위케어 블랙 황사 미세먼지마스크 KF94 성인용 60매","prodStatus":false,"prodPath":"https://smartstore.naver.com/wiicare/products/4242272411","index":20,"crawlTime":"2020-06-19T01:41:25.658Z","prodImg":"https://shop-phinf.pstatic.net/20200617_24/1592369212655rXook_JPEG/29732601169340890_462595779.jpg?type=m510"},{"prodName":"상품명: 위케어 바른생활 황사마스크 25매","prodStatus":false,"prodPath":"https://smartstore.naver.com/wiicare/products/4831400613","index":21,"crawlTime":"2020-06-19T01:41:30.483Z","prodImg":"https://shop-phinf.pstatic.net/20200224_76/15825036779107aFjP_JPEG/19864416541846422_1555633424.jpg?type=m510"},{"prodName":"상품명: 평편 미세먼지 황사 마스크 KF94 대형 10매 블랙,그린 랜덤발송","prodStatus":false,"prodPath":"https://smartstore.naver.com/pyeongpyoen/products/4751210548","index":22,"crawlTime":"2020-06-19T01:41:34.056Z","prodImg":"https://shop-phinf.pstatic.net/20200113_37/1578909726463iY1aO_JPEG/16273114987797129_995399569.jpg?type=m510"},{"prodName":"상품명: 뉴크린웰 KF80 대형/소형 황사 방역용 마스크 화이트 50매입","prodStatus":false,"prodPath":"https://smartstore.naver.com/pyeongpyoen/products/4690028600","index":23,"crawlTime":"2020-06-19T01:41:37.983Z","prodImg":"https://shop-phinf.pstatic.net/20200618_82/1592409405848ukqgs_PNG/29770948440995249_1086705447.png?type=m510"},{"prodName":"상품명: 네퓨어 비말 에스 마스크 KF-AD(대형) 30매","prodStatus":false,"prodPath":"https://smartstore.naver.com/echopear/products/4961501444","index":24,"crawlTime":"2020-06-19T01:41:41.771Z","prodImg":"https://shop-phinf.pstatic.net/20200614_105/1592112777504jPVR7_JPEG/29472612013943098_1728206665.jpg?type=m510"},{"prodName":"상품명: 뉴네퓨어 황사방역용마스크 KF94 대형 30p","prodStatus":false,"prodPath":"https://smartstore.naver.com/echopear/products/4196595736","index":25,"crawlTime":"2020-06-19T01:41:45.699Z","prodImg":"https://shop-phinf.pstatic.net/20200602_158/15910643695292JChs_JPEG/28426703109904224_1724163457.jpg?type=m510"},{"prodName":"상품명: 네퓨어 비말마스크 KF-AD 끈조절 식약처 허가","prodStatus":false,"prodPath":"https://smartstore.naver.com/realize7/products/4959734181","index":26,"crawlTime":"2020-06-19T01:41:50.838Z","prodImg":"https://shop-phinf.pstatic.net/20200616_181/1592283356417glcGJ_JPEG/29646744715250236_1861401228.jpg?type=m510"},{"prodName":"상품명: 비말 마스크 30매 네퓨어 KF-AD 끈조절 가능(개당 600원) 코로나 미세먼지 황사 마스크 (수량 1개로해서 결제하세요)","prodStatus":false,"prodPath":"https://smartstore.naver.com/deurimishop/products/4959000508","index":27,"crawlTime":"2020-06-19T01:41:54.584Z","prodImg":"https://shop-phinf.pstatic.net/20200616_99/1592283465157wC11l_JPEG/29646853657566595_966112910.jpg?type=m510"}]